LICENSE
README.md
pyproject.toml
setup.py
lite/__init__.py
lite/lite.py
lite/lite_collection.py
lite/lite_connection.py
lite/lite_exceptions.py
lite/lite_model.py
lite/lite_query.py
lite/lite_table.py
lite_py.egg-info/PKG-INFO
lite_py.egg-info/SOURCES.txt
lite_py.egg-info/dependency_links.txt
lite_py.egg-info/requires.txt
lite_py.egg-info/top_level.txt
tests/test_lite.py
tests/test_lite_collection.py
tests/test_lite_connection.py
tests/test_lite_model.py
tests/test_lite_query.py
tests/test_lite_table.py