Metadata-Version: 2.1
Name: lite-py
Version: 0.0.1
Summary: An SQLite ORM for Python, inspired by Laravel's Eloquent.
Author-email: Ben Moore <ben@benhmoore.com>
License-File: LICENSE
